enumgen/__init__.py
enumgen/__main__.py
enumgen/src/renderer.py
enumgen/templates/header.j2
enumgen/templates/src.j2
enumgen/templates/standalone.j2
enumgen-0.1.2.dist-info/METADATA
enumgen-0.1.2.dist-info/WHEEL
enumgen-0.1.2.dist-info/top_level.txt
enumgen-0.1.2.dist-info/RECORD
