Metadata-Version: 2.4
Name: enumgen
Version: 0.1.2
Summary: Application to generate C enumerations
Author-email: Alexander Smirnov <alexsm.w@yandex.ru>
License: MIT
Project-URL: Homepage, https://gitverse.ru/alexsm/enumgen
Requires-Python: >=3.8
Requires-Dist: jinja2>=3.1
Requires-Dist: commentjson==0.9
Provides-Extra: build
Requires-Dist: build>=1.3; extra == "build"
Requires-Dist: twine>=6.2; extra == "build"
